README.md
pyproject.toml
src/FMD3/__main__.py
src/FMD3/Core/__init__.py
src/FMD3/Core/hello.py
src/FMD3/Core/_database/__init__.py
src/FMD3/Core/logging/__init__.py
src/FMD3/Core/settings/Keys.py
src/FMD3/Core/settings/_SettingsDefault.py
src/FMD3/Core/settings/__init__.py
src/FMD3/Core/settings/models/SettingControl.py
src/FMD3/Core/settings/models/SettingControlType.py
src/FMD3/Core/settings/models/SettingSection.py
src/FMD3/Core/settings/models/__init__.py
src/FMD3/Extensions/IExtension.py
src/FMD3/Extensions/__init__.py
src/FMD3_ThePromidius.egg-info/PKG-INFO
src/FMD3_ThePromidius.egg-info/SOURCES.txt
src/FMD3_ThePromidius.egg-info/dependency_links.txt
src/FMD3_ThePromidius.egg-info/entry_points.txt
src/FMD3_ThePromidius.egg-info/top_level.txt