Metadata-Version: 2.1
Name: FMD3_ThePromidius
Version: 0.0.4
Summary: Super secret package :)
Author-email: ThePromidius <thepromidiusyt@gmail.com>
Project-URL: Homepage, https://github.com/MangaManagerORG/FMD3
Project-URL: Issues, https://github.com/MangaManagerORG/FMD3/issues
Classifier: Programming Language :: Python :: 3
Classifier: License :: OSI Approved :: MIT License
Classifier: Operating System :: OS Independent
Requires-Python: >=3.11
